{
  "sys": {
    "_semantic": {
      "colour": {
        "primary": {
          "value": "{colour.primary.500}",
          "type": "color"
        },
        "on-primary": {
          "value": "{colour.grayscale.white}",
          "type": "color"
        },
        "primary-surface": {
          "value": "{colour.primary.200}",
          "type": "color"
        },
        "on-primary-surface": {
          "value": "{colour.primary.700}",
          "type": "color"
        },
        "secondary": {
          "value": "{colour.secondary.500}",
          "type": "color",
          "description": "Secondary key colour"
        },
        "on-secondary": {
          "value": "{colour.grayscale.white}",
          "type": "color",
          "description": "Content on secondary"
        },
        "secondary-surface": {
          "value": "{colour.secondary.200}",
          "type": "color",
          "description": "Secondary support colour"
        },
        "on-secondary-surface": {
          "value": "{colour.secondary.700}",
          "type": "color",
          "description": "Content on secondary support"
        },
        "tertiary": {
          "value": "{colour.grayscale.white}",
          "type": "color"
        },
        "on-tertiary": {
          "value": "{colour.primary.500}",
          "type": "color"
        },
        "subtle": {
          "value": "rgba({colour.grayscale.white},0.00)",
          "type": "color"
        },
        "on-subtle": {
          "value": "{colour.primary.500}",
          "type": "color"
        },
        "neutral": {
          "value": "{colour.neutral.200}",
          "type": "color"
        },
        "disabled": {
          "value": "rgba({colour.neutral.500},0.12)",
          "type": "color",
          "description": "Disabled action background state"
        },
        "outline": {
          "value": "rgba({colour.neutral.600},0.44)",
          "type": "color",
          "description": "Component outline"
        },
        "transparent": {
          "value": "rgba({colour.grayscale.white},0.00)",
          "type": "color"
        }
      },
      "sentiment": {
        "error": {
          "value": "{colour.error.200}",
          "type": "color"
        },
        "success": {
          "value": "{colour.success.200}",
          "type": "color"
        },
        "warning": {
          "value": "{colour.warning.200}",
          "type": "color"
        },
        "info": {
          "value": "{colour.info.200}",
          "type": "color"
        },
        "error-surface": {
          "value": "{colour.error.100}",
          "type": "color"
        },
        "on-error-surface": {
          "value": "{colour.error.300}",
          "type": "color"
        },
        "success-surface": {
          "value": "{colour.success.100}",
          "type": "color"
        },
        "on-success-surface": {
          "value": "{colour.success.300}",
          "type": "color"
        },
        "warning-surface": {
          "value": "{colour.warning.100}",
          "type": "color"
        },
        "on-warning-surface": {
          "value": "{colour.warning.300}",
          "type": "color"
        },
        "info-surface": {
          "value": "{colour.info.100}",
          "type": "color"
        },
        "on-info-surface": {
          "value": "{colour.info.300}",
          "type": "color"
        }
      },
      "content": {
        "primary": {
          "value": "{colour.grayscale.black}",
          "type": "color"
        },
        "primary-inverse": {
          "value": "{colour.grayscale.white}",
          "type": "color"
        },
        "text-link": {
          "value": "{sys._semantic.colour.primary}",
          "type": "color"
        }
      }
    }
  }
}